COPYING
COPYING.lesser
MANIFEST.in
NOTICE
README.md
requirements.txt
setup.py
compiler/__init__.py
compiler/api/__init__.py
compiler/api/compiler.py
compiler/api/source/auth_key.tl
compiler/api/source/main_api.tl
compiler/api/source/sys_msgs.tl
compiler/api/template/combinator.txt
compiler/api/template/type.txt
compiler/errors/__init__.py
compiler/errors/compiler.py
compiler/errors/sort.py
compiler/errors/source/303_SEE_OTHER.tsv
compiler/errors/source/400_BAD_REQUEST.tsv
compiler/errors/source/401_UNAUTHORIZED.tsv
compiler/errors/source/403_FORBIDDEN.tsv
compiler/errors/source/406_NOT_ACCEPTABLE.tsv
compiler/errors/source/420_FLOOD.tsv
compiler/errors/source/500_INTERNAL_SERVER_ERROR.tsv
compiler/errors/source/503_SERVICE_UNAVAILABLE.tsv
compiler/errors/template/class.txt
compiler/errors/template/sub_class.txt
nan_dev/__init__.py
nan_dev/client.py
nan_dev/dispatcher.py
nan_dev/emoji.py
nan_dev/file_id.py
nan_dev/filters.py
nan_dev/listen.py
nan_dev/mime_types.py
nan_dev/py.typed
nan_dev/sync.py
nan_dev/utils.py
nan_dev.egg-info/PKG-INFO
nan_dev.egg-info/SOURCES.txt
nan_dev.egg-info/dependency_links.txt
nan_dev.egg-info/not-zip-safe
nan_dev.egg-info/requires.txt
nan_dev.egg-info/top_level.txt
nan_dev/connection/__init__.py
nan_dev/connection/connection.py
nan_dev/connection/transport/__init__.py
nan_dev/connection/transport/tcp/__init__.py
nan_dev/connection/transport/tcp/tcp.py
nan_dev/connection/transport/tcp/tcp_abridged.py
nan_dev/connection/transport/tcp/tcp_abridged_o.py
nan_dev/connection/transport/tcp/tcp_full.py
nan_dev/connection/transport/tcp/tcp_intermediate.py
nan_dev/connection/transport/tcp/tcp_intermediate_o.py
nan_dev/crypto/__init__.py
nan_dev/crypto/aes.py
nan_dev/crypto/mtproto.py
nan_dev/crypto/prime.py
nan_dev/crypto/rsa.py
nan_dev/dev/__init__.py
nan_dev/dev/pykeyboard/__init__.py
nan_dev/dev/pykeyboard/inline_keyboard.py
nan_dev/dev/pykeyboard/inline_pagination_keyboard.py
nan_dev/dev/pykeyboard/reply_keyboard.py
nan_dev/enums/__init__.py
nan_dev/enums/auto_name.py
nan_dev/enums/chat_action.py
nan_dev/enums/chat_event_action.py
nan_dev/enums/chat_member_status.py
nan_dev/enums/chat_members_filter.py
